jupyter_mcp_tools/__init__.py
jupyter_mcp_tools/_version.py
jupyter_mcp_tools/client.py
jupyter_mcp_tools/handlers.py
jupyter_mcp_tools/route.py
jupyter_mcp_tools/websocket.py
jupyter_mcp_tools/tests/__init__.py
jupyter_mcp_tools/tests/test_commandid_flow.py
jupyter_mcp_tools/tests/test_handlers.py
jupyter_mcp_tools/tests/test_integration.py
jupyter_mcp_tools/tests/test_mcp_client.py
jupyter_mcp_tools/tests/test_tool_name_validation.py
jupyter_mcp_tools-0.1.6.data/data/etc/jupyter/jupyter_server_config.d/jupyter_mcp_tools.json
jupyter_mcp_tools-0.1.6.data/data/share/jupyter/labextensions/@datalayer/jupyter-mcp-tools/package.json
jupyter_mcp_tools-0.1.6.data/data/share/jupyter/labextensions/@datalayer/jupyter-mcp-tools/schemas/@datalayer/jupyter-mcp-tools/package.json.orig
jupyter_mcp_tools-0.1.6.data/data/share/jupyter/labextensions/@datalayer/jupyter-mcp-tools/schemas/@datalayer/jupyter-mcp-tools/plugin.json
jupyter_mcp_tools-0.1.6.data/data/share/jupyter/labextensions/@datalayer/jupyter-mcp-tools/static/165.e00e6f93c4db4783b476.js
jupyter_mcp_tools-0.1.6.data/data/share/jupyter/labextensions/@datalayer/jupyter-mcp-tools/static/95.7ad29ed40910d10f4cce.js
jupyter_mcp_tools-0.1.6.data/data/share/jupyter/labextensions/@datalayer/jupyter-mcp-tools/static/remoteEntry.fcb57c9e99faa0af1c9e.js
jupyter_mcp_tools-0.1.6.data/data/share/jupyter/labextensions/@datalayer/jupyter-mcp-tools/static/style.js
jupyter_mcp_tools-0.1.6.data/data/share/jupyter/labextensions/@datalayer/jupyter-mcp-tools/static/third-party-licenses.json
jupyter_mcp_tools-0.1.6.data/data/share/jupyter/labextensions/@datalayer/jupyter-mcp-tools/install.json
jupyter_mcp_tools-0.1.6.dist-info/METADATA
jupyter_mcp_tools-0.1.6.dist-info/WHEEL
jupyter_mcp_tools-0.1.6.dist-info/licenses/LICENSE
jupyter_mcp_tools-0.1.6.dist-info/RECORD
